{"mean":{"confidence_interval":{"confidence_level":0.95,"lower_bound":421042.48724525905,"upper_bound":451430.6757646357},"point_estimate":435857.2249234936,"standard_error":7777.734339938555},"median":{"confidence_interval":{"confidence_level":0.95,"lower_bound":396518.77147147147,"upper_bound":426967.3333333333},"point_estimate":408587.21547619044,"standard_error":8060.9786766199295},"median_abs_dev":{"confidence_interval":{"confidence_level":0.95,"lower_bound":38591.070483169904,"upper_bound":92168.14589710989},"point_estimate":59449.37862712829,"standard_error":13722.312917777892},"slope":{"confidence_interval":{"confidence_level":0.95,"lower_bound":404220.0066005019,"upper_bound":432289.1546678511},"point_estimate":417145.51066843997,"standard_error":7150.494208987291},"std_dev":{"confidence_interval":{"confidence_level":0.95,"lower_bound":65241.419716380944,"upper_bound":91537.9087523707},"point_estimate":78344.45316195478,"standard_error":6765.082438906942}}