{"mean":{"confidence_interval":{"confidence_level":0.95,"lower_bound":51273.82060397887,"upper_bound":52831.00145502268},"point_estimate":52012.12559586522,"standard_error":397.1978745994242},"median":{"confidence_interval":{"confidence_level":0.95,"lower_bound":51228.733993506496,"upper_bound":52238.54230769231},"point_estimate":51666.54483359133,"standard_error":265.09794232676074},"median_abs_dev":{"confidence_interval":{"confidence_level":0.95,"lower_bound":1737.2122504083184,"upper_bound":3117.3294578013024},"point_estimate":2341.3967635857352,"standard_error":356.2763508801535},"slope":{"confidence_interval":{"confidence_level":0.95,"lower_bound":50781.35373807515,"upper_bound":53002.933458880965},"point_estimate":51800.60655992316,"standard_error":567.9348967086255},"std_dev":{"confidence_interval":{"confidence_level":0.95,"lower_bound":2778.523266006716,"upper_bound":5127.220174014},"point_estimate":3989.733717600769,"standard_error":603.1586815652948}}