{"mean":{"confidence_interval":{"confidence_level":0.95,"lower_bound":40828.859591745364,"upper_bound":41362.831035327465},"point_estimate":41103.2178786065,"standard_error":136.32013922574197},"median":{"confidence_interval":{"confidence_level":0.95,"lower_bound":41089.54181818182,"upper_bound":42083.42769230769},"point_estimate":41749.246,"standard_error":230.86867653699247},"median_abs_dev":{"confidence_interval":{"confidence_level":0.95,"lower_bound":287.4451411773776,"upper_bound":1654.0681192980574},"point_estimate":755.3307199501978,"standard_error":320.51022101338316},"slope":{"confidence_interval":{"confidence_level":0.95,"lower_bound":39865.135897428045,"upper_bound":40588.61778959297},"point_estimate":40213.682562080685,"standard_error":184.52650801720566},"std_dev":{"confidence_interval":{"confidence_level":0.95,"lower_bound":1167.9334297531907,"upper_bound":1545.3770636403194},"point_estimate":1373.8072264993446,"standard_error":96.65100223851961}}