{"mean":{"confidence_interval":{"confidence_level":0.95,"lower_bound":344580.8200489019,"upper_bound":359673.86309030245},"point_estimate":351666.1929451849,"standard_error":3865.6183270840156},"median":{"confidence_interval":{"confidence_level":0.95,"lower_bound":341203.4420062696,"upper_bound":348444.6785714286},"point_estimate":344885.1711538462,"standard_error":1772.880620629823},"median_abs_dev":{"confidence_interval":{"confidence_level":0.95,"lower_bound":12143.411584411357,"upper_bound":22284.36238179288},"point_estimate":16348.704685457804,"standard_error":2443.012021106652},"slope":{"confidence_interval":{"confidence_level":0.95,"lower_bound":351803.3653117024,"upper_bound":377912.11243111006},"point_estimate":363944.0276744988,"standard_error":6693.914439945377},"std_dev":{"confidence_interval":{"confidence_level":0.95,"lower_bound":25612.22915743875,"upper_bound":50891.274201819084},"point_estimate":38753.39858876103,"standard_error":6497.071095543215}}